ssp4onnx/__init__.py
ssp4onnx/__main__.py
ssp4onnx/onnx_network_split.py
ssp4onnx-1.0.4.dist-info/WHEEL
ssp4onnx-1.0.4.dist-info/entry_points.txt
ssp4onnx-1.0.4.dist-info/METADATA
ssp4onnx-1.0.4.dist-info/RECORD
