Metadata-Version: 2.4
Name: ssp4onnx
Version: 1.0.4
Summary: Simple Split for ONNX. A simple tool that automatically splits ONNX models of specified weight sizes.
Keywords: onnx,deep-learning,machine-learning
Author: Katsuya Hyodo
Author-email: Katsuya Hyodo <rmsdh122@yahoo.co.jp>
License-Expression: MIT
Classifier: Development Status :: 5 - Production/Stable
Classifier: Intended Audience :: Developers
Classifier: Intended Audience :: Science/Research
Classifier: License :: OSI Approved :: MIT License
Classifier: Operating System :: POSIX :: Linux
Classifier: Operating System :: Unix
Classifier: Programming Language :: Python :: 3
Classifier: Programming Language :: Python :: 3.10
Classifier: Programming Language :: Python :: 3.11
Classifier: Topic :: Scientific/Engineering :: Artificial Intelligence
Requires-Dist: numpy==1.26.4
Requires-Dist: onnx==1.19.1
Requires-Dist: onnx-graphsurgeon==0.5.8
Requires-Python: >=3.10.12
Project-URL: Homepage, https://github.com/PINTO0309/ssp4onnx
Project-URL: Repository, https://github.com/PINTO0309/ssp4onnx
Project-URL: Documentation, https://github.com/PINTO0309/ssp4onnx#readme
